[
  {
    "name":"Science",
    "subject": [
      {
        "question":" sc qn1",
        "rate":5,
        "answers": [
          {
            "answer": " sc qn answer 1",
            "author": "answer author",
            "rate":4,
            "answered-date":"01/01/2016"
          },
          {
            "answer": "sc qn answer 2",
            "author": "answer author",
            "rate":3,
            "answered-date":"01/01/2016"
          },
          {
            "answer": "sc qn answer 3",
            "author": "answer author",
            "rate":2,
            "answered-date":"01/01/2016"
          },
          {
            "answer": "sc qn answer 4",
            "author": "answer author",
            "rate":5,
            "answered-date":"01/01/2016"
          }
        ]
      },
      {
        "question":" sc qn2",
        "rate":2,
        "answers": [
          {
            "answer": "sc qn2 answer 1",
            "author": "answer author",
            "rate":4,
            "answered-date":"01/01/2016"
          },
          {
            "answer": "sc qn2 answer 2",
            "author": "answer author",
            "rate":3,
            "answered-date":"01/01/2016"
          },
          {
            "answer": "sc qn2 answer 3",
            "author": "answer author",
            "rate":2,
            "answered-date":"01/01/2016"
          },
          {
            "answer": "sc qn2 answer 4",
            "author": "answer author",
            "rate":5,
            "answered-date":"01/01/2016"
          }
        ]
      },
      {
        "question":" sc qn3",
        "rate":3,
        "answers": [
          {
            "answer": "sc qn3 answer 1",
            "author": "answer author",
            "rate":4,
            "answered-date":"01/01/2016"
          },
          {
            "answer": "sc qn3 answer 2",
            "author": "answer author",
            "rate":3,
            "answered-date":"01/01/2016"
          },
          {
            "answer": "sc qn3 answer 3",
            "author": "answer author",
            "rate":2,
            "answered-date":"01/01/2016"
          },
          {
            "answer": "sc qn3 answer 4",
            "author": "answer author",
            "rate":5,
            "answered-date":"01/01/2016"
          }
        ]
      }

    ]
  },
  {
    "name":"Technology",
    "subject": [
      {
        "question":"qn1",
        "rate":5,
        "answers": [
          {
            "answer": "qn answer",
            "author": "answer author",
            "rate":4,
            "answered-date":"01/01/2016"
          },
          {
            "answer": "qn answer",
            "author": "answer author",
            "rate":3,
            "answered-date":"01/01/2016"
          },
          {
            "answer": "qn answer",
            "author": "answer author",
            "rate":2,
            "answered-date":"01/01/2016"
          },
          {
            "answer": "qn answer",
            "author": "answer author",
            "rate":5,
            "answered-date":"01/01/2016"
          }
        ]
      },
      {
        "question":"qn2",
        "rate":2,
        "answers": [
          {
            "answer": "qn answer",
            "author": "answer author",
            "rate":4,
            "answered-date":"01/01/2016"
          },
          {
            "answer": "qn answer",
            "author": "answer author",
            "rate":3
          },
          {
            "answer": "qn answer",
            "author": "answer author",
            "rate":2,
            "answered-date":"01/01/2016"
          },
          {
            "answer": "qn answer",
            "author": "answer author",
            "rate":5,
            "answered-date":"01/01/2016"
          }
        ]
      },
      {
        "question":"qn3",
        "rate":3,
        "answers": [
          {
            "answer": "qn answer",
            "author": "answer author",
            "rate":4,
            "answered-date":"01/01/2016"
          },
          {
            "answer": "qn answer",
            "author": "answer author",
            "rate":3,
            "answered-date":"01/01/2016"
          },
          {
            "answer": "qn answer",
            "author": "answer author",
            "rate":2,
            "answered-date":"01/01/2016"
          },
          {
            "answer": "qn answer",
            "author": "answer author",
            "rate":5,
            "answered-date":"01/01/2016"
          }
        ]
      },
      {
        "question":"qn4",
        "rate":0.3,
        "answers": [
          {
            "answer": "qn answer",
            "author": "answer author",
            "rate":4,
            "answered-date":"01/01/2016"
          },
          {
            "answer": "qn answer",
            "author": "answer author",
            "rate":3,
            "answered-date":"01/01/2016"
          },
          {
            "answer": "qn answer",
            "author": "answer author",
            "rate":2,
            "answered-date":"01/01/2016"
          },
          {
            "answer": "qn answer",
            "author": "answer author",
            "rate":5,
            "answered-date":"01/01/2016"
          }
        ]
      },
      {
        "question":"qn1",
        "rate":5,
        "answers": [
          {
            "answer": "qn answer",
            "author": "answer author",
            "rate":4,
            "answered-date":"01/01/2016"
          },
          {
            "answer": "qn answer",
            "author": "answer author",
            "rate":3,
            "answered-date":"01/01/2016"
          },
          {
            "answer": "qn answer",
            "author": "answer author",
            "rate":2,
            "answered-date":"01/01/2016"
          },
          {
            "answer": "qn answer",
            "author": "answer author",
            "rate":5,
            "answered-date":"01/01/2016"
          }
        ]
      }

    ]
  },
  {
    "name":"Army",
    "subject": [
      {
        "question":"qn1",
        "rate":5,
        "answers": [
          {
            "answer": "qn answer",
            "author": "answer author",
            "rate":4,
            "answered-date":"01/01/2016"
          },
          {
            "answer": "qn answer",
            "author": "answer author",
            "rate":3,
            "answered-date":"01/01/2016"
          },
          {
            "answer": "qn answer",
            "author": "answer author",
            "rate":2,
            "answered-date":"01/01/2016"
          },
          {
            "answer": "qn answer",
            "author": "answer author",
            "rate":5,
            "answered-date":"01/01/2016"
          }
        ]
      },
      {
        "question":"qn2",
        "rate":2,
        "answers": [
          {
            "answer": "qn answer",
            "author": "answer author",
            "rate":4,
            "answered-date":"01/01/2016"
          },
          {
            "answer": "qn answer",
            "author": "answer author",
            "rate":3
          },
          {
            "answer": "qn answer",
            "author": "answer author",
            "rate":2,
            "answered-date":"01/01/2016"
          },
          {
            "answer": "qn answer",
            "author": "answer author",
            "rate":5,
            "answered-date":"01/01/2016"
          }
        ]
      },
      {
        "question":"qn3",
        "rate":3,
        "answers": [
          {
            "answer": "qn answer",
            "author": "answer author",
            "rate":4,
            "answered-date":"01/01/2016"
          },
          {
            "answer": "qn answer",
            "author": "answer author",
            "rate":3,
            "answered-date":"01/01/2016"
          },
          {
            "answer": "qn answer",
            "author": "answer author",
            "rate":2,
            "answered-date":"01/01/2016"
          },
          {
            "answer": "qn answer",
            "author": "answer author",
            "rate":5,
            "answered-date":"01/01/2016"
          }
        ]
      },
      {
        "question":"qn4",
        "rate":0.3,
        "answers": [
          {
            "answer": "qn answer",
            "author": "answer author",
            "rate":4,
            "answered-date":"01/01/2016"
          },
          {
            "answer": "qn answer",
            "author": "answer author",
            "rate":3,
            "answered-date":"01/01/2016"
          },
          {
            "answer": "qn answer",
            "author": "answer author",
            "rate":2,
            "answered-date":"01/01/2016"
          },
          {
            "answer": "qn answer",
            "author": "answer author",
            "rate":5,
            "answered-date":"01/01/2016"
          }
        ]
      }

    ]
  },
  {
    "name":"India",
    "subject": [
      {
        "question":"qn1",
        "rate":5,
        "answers": [
          {
            "answer": "qn answer",
            "author": "answer author",
            "rate":4,
            "answered-date":"01/01/2016"
          },
          {
            "answer": "qn answer",
            "author": "answer author",
            "rate":3,
            "answered-date":"01/01/2016"
          },
          {
            "answer": "qn answer",
            "author": "answer author",
            "rate":2,
            "answered-date":"01/01/2016"
          },
          {
            "answer": "qn answer",
            "author": "answer author",
            "rate":5,
            "answered-date":"01/01/2016"
          }
        ]
      },
      {
        "question":"qn2",
        "rate":2,
        "answers": [
          {
            "answer": "qn answer",
            "author": "answer author",
            "rate":4,
            "answered-date":"01/01/2016"
          },
          {
            "answer": "qn answer",
            "author": "answer author",
            "rate":3
          },
          {
            "answer": "qn answer",
            "author": "answer author",
            "rate":2,
            "answered-date":"01/01/2016"
          },
          {
            "answer": "qn answer",
            "author": "answer author",
            "rate":5,
            "answered-date":"01/01/2016"
          }
        ]
      },
      {
        "question":"qn3",
        "rate":3,
        "answers": [
          {
            "answer": "qn answer",
            "author": "answer author",
            "rate":4,
            "answered-date":"01/01/2016"
          },
          {
            "answer": "qn answer",
            "author": "answer author",
            "rate":3,
            "answered-date":"01/01/2016"
          },
          {
            "answer": "qn answer",
            "author": "answer author",
            "rate":2,
            "answered-date":"01/01/2016"
          },
          {
            "answer": "qn answer",
            "author": "answer author",
            "rate":5,
            "answered-date":"01/01/2016"
          }
        ]
      }

    ]
  },
  {
    "name":"Agriculture",
    "subject": [
      {
        "question":"qn1",
        "rate":5,
        "answers": [
          {
            "answer": "qn answer",
            "author": "answer author",
            "rate":4,
            "answered-date":"01/01/2016"
          },
          {
            "answer": "qn answer",
            "author": "answer author",
            "rate":3,
            "answered-date":"01/01/2016"
          },
          {
            "answer": "qn answer",
            "author": "answer author",
            "rate":2,
            "answered-date":"01/01/2016"
          },
          {
            "answer": "qn answer",
            "author": "answer author",
            "rate":5,
            "answered-date":"01/01/2016"
          }
        ]
      },
      {
        "question":"qn2",
        "rate":2,
        "answers": [
          {
            "answer": "qn answer",
            "author": "answer author",
            "rate":4,
            "answered-date":"01/01/2016"
          },
          {
            "answer": "qn answer",
            "author": "answer author",
            "rate":3
          },
          {
            "answer": "qn answer",
            "author": "answer author",
            "rate":2,
            "answered-date":"01/01/2016"
          },
          {
            "answer": "qn answer",
            "author": "answer author",
            "rate":5,
            "answered-date":"01/01/2016"
          }
        ]
      },
      {
        "question":"qn3",
        "rate":3,
        "answers": [
          {
            "answer": "qn answer",
            "author": "answer author",
            "rate":4,
            "answered-date":"01/01/2016"
          },
          {
            "answer": "qn answer",
            "author": "answer author",
            "rate":3,
            "answered-date":"01/01/2016"
          },
          {
            "answer": "qn answer",
            "author": "answer author",
            "rate":2,
            "answered-date":"01/01/2016"
          },
          {
            "answer": "qn answer",
            "author": "answer author",
            "rate":5,
            "answered-date":"01/01/2016"
          }
        ]
      },
      {
        "question":"qn4",
        "rate":0.3,
        "answers": [
          {
            "answer": "qn answer",
            "author": "answer author",
            "rate":4,
            "answered-date":"01/01/2016"
          },
          {
            "answer": "qn answer",
            "author": "answer author",
            "rate":3,
            "answered-date":"01/01/2016"
          },
          {
            "answer": "qn answer",
            "author": "answer author",
            "rate":2,
            "answered-date":"01/01/2016"
          },
          {
            "answer": "qn answer",
            "author": "answer author",
            "rate":5,
            "answered-date":"01/01/2016"
          }
        ]
      },
      {
        "question":"qn5",
        "rate":3,
        "answers": [
          {
            "answer": "qn answer",
            "author": "answer author",
            "rate":4,
            "answered-date":"01/01/2016"
          },
          {
            "answer": "qn answer",
            "author": "answer author",
            "rate":3,
            "answered-date":"01/01/2016"
          },
          {
            "answer": "qn answer",
            "author": "answer author",
            "rate":2,
            "answered-date":"01/01/2016"
          },
          {
            "answer": "qn answer",
            "author": "answer author",
            "rate":5,
            "answered-date":"01/01/2016"
          }
        ]
      },
      {
        "question":"qn5",
        "rate":3,
        "answers": [
          {
            "answer": "qn answer",
            "author": "answer author",
            "rate":4,
            "answered-date":"01/01/2016"
          },
          {
            "answer": "qn answer",
            "author": "answer author",
            "rate":3,
            "answered-date":"01/01/2016"
          },
          {
            "answer": "qn answer",
            "author": "answer author",
            "rate":2,
            "answered-date":"01/01/2016"
          },
          {
            "answer": "qn answer",
            "author": "answer author",
            "rate":5,
            "answered-date":"01/01/2016"
          }
        ]
      }

    ]
  },
  {
    "name":"Navy",
    "subject": [
      {
        "question":"qn1",
        "rate":5,
        "answers": [
          {
            "answer": "qn answer",
            "author": "answer author",
            "rate":4,
            "answered-date":"01/01/2016"
          },
          {
            "answer": "qn answer",
            "author": "answer author",
            "rate":3,
            "answered-date":"01/01/2016"
          },
          {
            "answer": "qn answer",
            "author": "answer author",
            "rate":2,
            "answered-date":"01/01/2016"
          },
          {
            "answer": "qn answer",
            "author": "answer author",
            "rate":5,
            "answered-date":"01/01/2016"
          }
        ]
      },
      {
        "question":"qn2",
        "rate":2,
        "answers": [
          {
            "answer": "qn answer",
            "author": "answer author",
            "rate":4,
            "answered-date":"01/01/2016"
          },
          {
            "answer": "qn answer",
            "author": "answer author",
            "rate":3
          },
          {
            "answer": "qn answer",
            "author": "answer author",
            "rate":2,
            "answered-date":"01/01/2016"
          },
          {
            "answer": "qn answer",
            "author": "answer author",
            "rate":5,
            "answered-date":"01/01/2016"
          }
        ]
      },
      {
        "question":"qn3",
        "rate":3,
        "answers": [
          {
            "answer": "qn answer",
            "author": "answer author",
            "rate":4,
            "answered-date":"01/01/2016"
          },
          {
            "answer": "qn answer",
            "author": "answer author",
            "rate":3,
            "answered-date":"01/01/2016"
          },
          {
            "answer": "qn answer",
            "author": "answer author",
            "rate":2,
            "answered-date":"01/01/2016"
          },
          {
            "answer": "qn answer",
            "author": "answer author",
            "rate":5,
            "answered-date":"01/01/2016"
          }
        ]
      }

    ]
  }
]
